colorcamp/__init__.py
colorcamp/_camp.py
colorcamp/_color_metadata.py
colorcamp/_report.py
colorcamp/_settings.py
colorcamp/color_space/__init__.py
colorcamp/color_space/_base_color.py
colorcamp/color_space/_hex.py
colorcamp/color_space/_hsl.py
colorcamp/color_space/_rgb.py
colorcamp/common/__init__.py
colorcamp/common/exceptions.py
colorcamp/common/types.py
colorcamp/common/validators.py
colorcamp/conversions.py
colorcamp/data/carto.json
colorcamp/data/colorbrewer.json
colorcamp/data/crayons.json
colorcamp/data/seaborn.json
colorcamp/data/web_colors.json
colorcamp/groups/__init__.py
colorcamp/groups/_color_group.py
colorcamp/groups/_map.py
colorcamp/groups/_palette.py
colorcamp/groups/_scale.py
colorcamp/static/html_templates.py
colorcamp/static/report.css
colorcamp/tests/conftest.py
colorcamp/tests/test_camp.py
colorcamp/tests/test_color.py
colorcamp/tests/test_color_group.py
colorcamp/tests/test_color_metadata.py
colorcamp/tests/test_conversions.py
colorcamp/tests/test_map.py
colorcamp/tests/test_palette.py
colorcamp/tests/test_scale.py
colorcamp/tests/test_validators.py
colorcamp-0.3.0.dist-info/LICENSE
colorcamp-0.3.0.dist-info/METADATA
colorcamp-0.3.0.dist-info/WHEEL
colorcamp-0.3.0.dist-info/RECORD
