Metadata-Version: 2.1
Name: colorcamp
Version: 0.3.0
Summary: A collection of colors is a Camp!
Home-page: https://github.com/DrAthanas/ColorCamp
License: Apache-2.0
Keywords: color,palette,colormap,camp,plotting
Author: Argus J Athanas
Author-email: argus@athanas.org
Requires-Python: >=3.9,<4.0
Classifier: Development Status :: 4 - Beta
Classifier: Framework :: Jupyter
Classifier: Framework :: Pytest
Classifier: Intended Audience :: Developers
Classifier: Intended Audience :: Science/Research
Classifier: License :: OSI Approved :: Apache Software License
Classifier: Natural Language :: English
Classifier: Programming Language :: Python :: 3
Classifier: Programming Language :: Python :: 3.9
Classifier: Programming Language :: Python :: 3.10
Classifier: Programming Language :: Python :: 3.11
Classifier: Programming Language :: Python :: 3.12
Classifier: Topic :: Artistic Software
Classifier: Topic :: Multimedia :: Graphics
Classifier: Topic :: Scientific/Engineering
Classifier: Typing :: Typed
Project-URL: Repository, https://github.com/DrAthanas/ColorCamp
